PhotoPy/__init__.py
PhotoPy/convolution.py
PhotoPy/histograma.py
PhotoPy/save.py
PhotoPy/texture_attributes.py
PhotoPy/filters/__init__.py
PhotoPy/filters/linear.py
PhotoPy/filters/noise.py
PhotoPy/filters/nonlinear.py
PhotoPy/reading/__init__.py
PhotoPy/reading/multiple_reading.py
PhotoPy-0.0.5.dist-info/METADATA
PhotoPy-0.0.5.dist-info/WHEEL
PhotoPy-0.0.5.dist-info/top_level.txt
PhotoPy-0.0.5.dist-info/RECORD
