Metadata-Version: 2.1
Name: PhotoPy
Version: 0.0.5
Summary: Biblioteca criada para a alterações e manipulações de imagens
Author: Augusto Almondes and Rafael Barbosa
Author-email: augusto7666@gmail.com
Keywords: python,PhotoPy,Image
Classifier: Programming Language :: Python :: 2
Classifier: Programming Language :: Python :: 3
Classifier: License :: OSI Approved :: MIT License
Classifier: Operating System :: OS Independent
Classifier: Development Status :: 3 - Alpha
Classifier: Intended Audience :: Education
Classifier: Operating System :: MacOS :: MacOS X
Classifier: Operating System :: Microsoft :: Windows
Requires-Dist: numpy
Requires-Dist: opencv-python
